LICENSE
MANIFEST.in
README.rst
setup.py
srim_srout/__init__.py
srim_srout/parser.py
srim_srout/stoppingunit.py
srim_srout/version.py
srim_srout.egg-info/PKG-INFO
srim_srout.egg-info/SOURCES.txt
srim_srout.egg-info/dependency_links.txt
srim_srout.egg-info/entry_points.txt
srim_srout.egg-info/not-zip-safe
srim_srout.egg-info/top_level.txt