Metadata-Version: 1.1
Name: srim-srout
Version: 0.1.2
Summary: Tools for SRIM SR output
Home-page: https://github.com/takaakiaoki/srim_srout/
Author: Takaaki AOKI
Author-email: aoki.takaaki.6v@kyoto-u.ac.jp
License: UNKNOWN
Platform: UNKNOWN
Classifier: Programming Language :: Python
Classifier: Programming Language :: Python :: 3.4
Classifier: License :: OSI Approved :: MIT License
Classifier: Development Status :: 4 - Beta
Classifier: Environment :: Other Environment
Classifier: Intended Audience :: Science/Research
Classifier: Operating System :: OS Independent
Classifier: Operating System :: Microsoft :: Windows :: Windows 7
Classifier: Topic :: Scientific/Engineering :: Physics
